LICENSE.md
MANIFEST.in
README.md
setup.py
temperusb/__init__.py
temperusb/cli.py
temperusb/device_library.py
temperusb/snmp.py
temperusb/temper.py
temperusb.egg-info/PKG-INFO
temperusb.egg-info/SOURCES.txt
temperusb.egg-info/dependency_links.txt
temperusb.egg-info/entry_points.txt
temperusb.egg-info/requires.txt
temperusb.egg-info/top_level.txt