Metadata-Version: 2.1
Name: temperusb
Version: 1.6.0
Summary: Reads temperature from TEMPerV1 devices (USB 0c45:7401)
Home-page: https://github.com/padelt/temper-python
Author: Philipp Adelt
Author-email: autosort-github@philipp.adelt.net 
License: UNKNOWN
Platform: UNKNOWN
Classifier: Development Status :: 5 - Production/Stable
Classifier: Environment :: Console
Classifier: License :: OSI Approved :: GNU General Public License v3 (GPLv3)
Classifier: Programming Language :: Python :: 2
Classifier: Programming Language :: Python :: 3
License-File: LICENSE.md
